lexikanon/__cli__.py
lexikanon/__init__.py
lexikanon/_version.py
lexikanon/conf/__init__.py
lexikanon/conf/about/lexikanon.yaml
lexikanon/conf/normalizer/__init__.yaml
lexikanon/conf/normalizer/formal_en.yaml
lexikanon/conf/normalizer/formal_en_parantheses.yaml
lexikanon/conf/normalizer/formal_ko.yaml
lexikanon/conf/normalizer/ftfy/__init__.yaml
lexikanon/conf/normalizer/informal_ko.yaml
lexikanon/conf/normalizer/spaces/__init__.yaml
lexikanon/conf/normalizer/special_characters/__init__.yaml
lexikanon/conf/pipe/extract_nouns.yaml
lexikanon/conf/pipe/extract_tokens.yaml
lexikanon/conf/pipe/find_similar_docs_by_clustering.yaml
lexikanon/conf/pipe/tokenize_dataset.yaml
lexikanon/conf/run/extract_tokens.yaml
lexikanon/conf/run/find_similar_docs_by_clustering.yaml
lexikanon/conf/run/tokenize_dataset.yaml
lexikanon/conf/stopwords/__init__.yaml
lexikanon/conf/tokenizer/__init__.yaml
lexikanon/conf/tokenizer/mecab.yaml
lexikanon/conf/tokenizer/nltk.yaml
lexikanon/conf/tokenizer/nltk_universal.yaml
lexikanon/conf/tokenizer/simple.yaml
lexikanon/conf/tokenizer/tagger/mecab.yaml
lexikanon/conf/tokenizer/tagger/nltk.yaml
lexikanon/conf/tokenizer/tagger/nltk_universal.yaml
lexikanon/normalizers/__init__.py
lexikanon/normalizers/normalizer.py
lexikanon/pipes/__init__.py
lexikanon/pipes/similarity.py
lexikanon/pipes/tokenize.py
lexikanon/py.typed
lexikanon/resources/dictionaries/mecab/ekon_v1.dic
lexikanon/stopwords/__init__.py
lexikanon/stopwords/stopwords.py
lexikanon/tokenizers/__init__.py
lexikanon/tokenizers/base.py
lexikanon/tokenizers/mecab.py
lexikanon/tokenizers/nltk.py
lexikanon/utils/__init__.py
lexikanon/utils/hangle.py
lexikanon/utils/hanja/__init__.py
lexikanon/utils/hanja/hangul.py
lexikanon/utils/hanja/impl.py
lexikanon/utils/hanja/table.py
lexikanon/utils/hanja/table.yml
lexikanon-0.6.5.dist-info/LICENSE
lexikanon-0.6.5.dist-info/METADATA
lexikanon-0.6.5.dist-info/WHEEL
lexikanon-0.6.5.dist-info/entry_points.txt
lexikanon-0.6.5.dist-info/RECORD
