Metadata-Version: 2.1
Name: lexikanon
Version: 0.6.5
Summary: A Python Library for Tokenizers
Home-page: https://lexikanon.entelecheia.ai
License: MIT
Author: Young Joon Lee
Author-email: entelecheia@hotmail.com
Requires-Python: >=3.9,<3.13
Classifier: License :: OSI Approved :: MIT License
Classifier: Programming Language :: Python :: 3
Classifier: Programming Language :: Python :: 3.9
Classifier: Programming Language :: Python :: 3.10
Classifier: Programming Language :: Python :: 3.11
Classifier: Programming Language :: Python :: 3.12
Requires-Dist: click (>=8.1.3,<9.0.0)
Requires-Dist: ekonlpy (==2.0.4)
Requires-Dist: ftfy (>=6.1.1,<7.0.0)
Requires-Dist: hyfi (>=1.36.3,<2.0.0)
Requires-Dist: nltk (>=3.8.1,<4.0.0)
Requires-Dist: scikit-learn (>=1.3.0,<2.0.0)
Project-URL: Repository, https://github.com/entelecheia/lexikanon
